fftx/__init__.py
fftx/convo.py
fftx/fft.py
fftx-1.0.3.data/data/share/fftx/Contributing.md
fftx-1.0.3.data/data/share/fftx/README.md
fftx-1.0.3.data/data/share/fftx/examples/run-fft.py
fftx-1.0.3.data/data/share/fftx/examples/run-fftn.py
fftx-1.0.3.data/data/share/fftx/examples/run-mdrconv.py
fftx-1.0.3.data/data/share/fftx/examples/run-mdrfsconv.py
fftx-1.0.3.data/data/share/fftx/examples/run-rfftn.py
fftx-1.0.3.data/data/share/fftx/examples/run-stepphase.py
fftx-1.0.3.data/data/share/fftx/examples/test-many.sh
fftx-1.0.3.data/data/share/fftx/examples/time-fftn.py
fftx-1.0.3.dist-info/LICENSE
fftx-1.0.3.dist-info/METADATA
fftx-1.0.3.dist-info/WHEEL
fftx-1.0.3.dist-info/top_level.txt
fftx-1.0.3.dist-info/RECORD
