Metadata-Version: 2.1
Name: fftx
Version: 1.0.3
Summary: A Python front end to access the FFTX Project
Home-page: https://github.com/spiral-software/python-package-fftx
Author: SpiralGen Inc.
Author-email: Patrick.Broderick@spiralgen.com, Mike.Franusich@spiralgen.com
Maintainer: ['Patrick Broderick', 'Mike Franusich']
Maintainer-email: Patrick.Broderick@spiralgen.com, Mike.Franusich@spiralgen.com
License: BSD-3-Clause
Project-URL: Source Code, https://github.com/spiral-software/python-package-fftx
Requires-Python: >=3.7
License-File: LICENSE
Requires-Dist: spiralpy>=1.0.4
